foma/__init__.py
foma/attapply.py
foma/foma2js.py
foma/phonrule.py
foma-1.0.0.dist-info/LICENSE
foma-1.0.0.dist-info/METADATA
foma-1.0.0.dist-info/WHEEL
foma-1.0.0.dist-info/top_level.txt
foma-1.0.0.dist-info/RECORD
