Metadata-Version: 2.1
Name: foma
Version: 1.0.0
Summary: Python bindings for Foma
Home-page: https://github.com/GooDeeJaY/foma-py
Author: Mans Hulden
Author-email: mans.hulden@gmail.com
Maintainer: Jasur Yusupov
Maintainer-email: jasuryusupov14@gmail.com
License: MIT
Project-URL: Bug Tracker, https://github.com/GooDeeJaY/foma-py/issues
Platform: UNKNOWN
Classifier: Programming Language :: Python :: 3
Classifier: License :: OSI Approved :: MIT License
Classifier: Operating System :: OS Independent
Requires-Python: >=3.6
License-File: LICENSE
